Metadata-Version: 2.1
Name: Flask
Version: 2.2.4
Summary: A simple framework for building complex web applications.
Home-page: https://palletsprojects.com/p/flask
Author: Armin Ronacher
Author-email: armin.ronacher@active-4.com
Maintainer: Pallets
Maintainer-email: contact@palletsprojects.com
License: BSD-3-Clause
Project-URL: Donate, https://palletsprojects.com/donate
Project-URL: Documentation, https://flask.palletsprojects.com/
Project-URL: Changes, https://flask.palletsprojects.com/changes/
Project-URL: Source Code, https://github.com/pallets/flask/
Project-URL: Issue Tracker, https://github.com/pallets/flask/issues/
Project-URL: Twitter, https://twitter.com/PalletsTeam
Project-URL: Chat, https://discord.gg/pallets
Classifier: Development Status :: 5 - Production/Stable
Classifier: Environment :: Web Environment
Classifier: Framework :: Flask
Classifier: Intended Audience :: Developers
Classifier: License :: OSI Approved :: BSD License
Classifier: Operating System :: OS Independent
Classifier: Programming Language :: Python
Classifier: Topic :: Internet :: WWW/HTTP :: Dynamic Content
Classifier: Topic :: Internet :: WWW/HTTP :: WSGI
Classifier: Topic :: Internet :: WWW/HTTP :: WSGI :: Application
Classifier: Topic :: Software Development :: Libraries :: Application Frameworks
Requires-Python: >=3.7
Provides-Extra: async
Provides-Extra: dotenv
License-File: LICENSE.rst
